<?xml version="1.0" encoding="UTF-8"?>
<beans
	xmlns="http://www.springframework.org/schema/beans"
	xmlns:media="http://www.riotfamily.org/schema/media/setup"
	xmlns:p="http://www.riotfamily.org/schema/content/page"
	xmlns:xsi="http://www.w3.org/2001/XMLSchema-instance"
	xsi:schemaLocation="
		http://www.springframework.org/schema/beans
		http://www.springframework.org/schema/beans/spring-beans-3.0.xsd
		http://www.riotfamily.org/schema/content/page
		http://www.riotfamily.org/schema/content/page-9.0.xsd
		http://www.riotfamily.org/schema/media/setup
		http://www.riotfamily.org/schema/media/setup-9.0.xsd">
	
	<bean id="defaultPageController" class="org.riotfamily.common.web.controller.CacheableViewController" />
	
	<p:schema name="default">
		<p:root-page>
			<p:handler>
				<bean class="org.riotfamily.pages.controller.FolderController" />
			</p:handler>
			
			<p:type name="default" handler="defaultPageController">
				<p:type-ref name="default" />
				<p:type name="wide" handler="defaultPageController">
					<p:type-ref name="default" />
				</p:type>
			</p:type>
			
			<!-- Wide pages are available below / too -->
			<p:type-ref name="wide" />
			
			<p:system-page name="home">
				<p:handler>
					<!-- Comment out the below and add a home.ftl in pages...
					<ref bean="defaultPageController" />
					... or just set the view name to a custom template below.
					-->
					<bean parent="defaultPageController">
						<property name="viewName" value="pages/default.ftl" />
					</bean>				
				</p:handler>
				<!-- 
				<p:prop key="title" value="Hello World" />
				 -->
			</p:system-page>
						
			<p:system-page name="pets">
				<p:handler>
					<bean class="org.riotfamily.common.web.controller.CacheableViewController">
						<property name="viewName" value="pages/pet-list.ftl" />
					</bean>
				</p:handler>
				<p:virtual-page name="pet">
					<p:resolver>
						<bean class="org.riotfamily.example.petstore.PetPageResolver" />
					</p:resolver>
					<p:handler>
						<ref bean="defaultPageController" />
					</p:handler>
				</p:virtual-page>
			</p:system-page>
		
		</p:root-page>
	</p:schema>

</beans>